{
  "routes": [
    {
      "method": "GET",
      "path": "/casts",
      "handler": "cast.find",
      "config": {
        "policies": []
      }
    },
    {
      "method": "GET",
      "path": "/casts/count",
      "handler": "cast.count",
      "config": {
        "policies": []
      }
    },
    {
      "method": "GET",
      "path": "/casts/:id",
      "handler": "cast.findOne",
      "config": {
        "policies": []
      }
    },
    {
      "method": "POST",
      "path": "/casts",
      "handler": "cast.create",
      "config": {
        "policies": []
      }
    },
    {
      "method": "PUT",
      "path": "/casts/:id",
      "handler": "cast.update",
      "config": {
        "policies": []
      }
    },
    {
      "method": "DELETE",
      "path": "/casts/:id",
      "handler": "cast.delete",
      "config": {
        "policies": []
      }
    }
  ]
}
